xraygpt/__about__.py
xraygpt/__init__.py
xraygpt/__main__.py
xraygpt/flow.py
xraygpt/llm.py
xraygpt/output.py
xraygpt/reader.py
xraygpt/splitter.py
xraygpt/db/base.py
xraygpt/db/chroma.py
xraygpt/db/text_cache.py
xraygpt/ner/agent.py
xraygpt/ner/azure.py
xraygpt/xraydb/README.md
xraygpt/xraydb/__init__.py
xraygpt/xraydb/init_script.py
xraygpt/xraydb/types.py
xraygpt/xraydb/xray.py
xraygpt-0.2.10.post0.dist-info/METADATA
xraygpt-0.2.10.post0.dist-info/WHEEL
xraygpt-0.2.10.post0.dist-info/licenses/LICENSE
xraygpt-0.2.10.post0.dist-info/RECORD
