Metadata-Version: 2.4
Name: xraygpt
Version: 0.2.10.post0
Summary: Generate kindle-like x-ray for e-books with LLM
Project-URL: homepage, https://github.com/iaalm/xraygpt
Project-URL: repository, https://github.com/iaalm/xraygpt
Project-URL: documentation, https://github.com/iaalm/xraygpt
Author-email: iaalm <iaalmsimon@gmail.com>
License: BSD-3
License-File: LICENSE
Classifier: Development Status :: 3 - Alpha
Classifier: Intended Audience :: Science/Research
Classifier: License :: OSI Approved :: BSD License
Classifier: Programming Language :: Python :: 3 :: Only
Requires-Python: >=3.9
Requires-Dist: beautifulsoup4
Requires-Dist: ebooklib
Requires-Dist: langchain-chroma
Requires-Dist: langchain-community
Requires-Dist: langchain-openai
Requires-Dist: langchain>=0.3
Requires-Dist: loguru
Provides-Extra: all
Requires-Dist: azure-ai-textanalytics; extra == 'all'
Requires-Dist: azure-core; extra == 'all'
Provides-Extra: azure
Requires-Dist: azure-ai-textanalytics; extra == 'azure'
Requires-Dist: azure-core; extra == 'azure'
Provides-Extra: dev
Requires-Dist: azure-ai-textanalytics; extra == 'dev'
Requires-Dist: azure-core; extra == 'dev'
Requires-Dist: black; extra == 'dev'
Requires-Dist: build; extra == 'dev'
Requires-Dist: hatch; extra == 'dev'
Requires-Dist: isort; extra == 'dev'
Requires-Dist: mypy; extra == 'dev'
Requires-Dist: q; extra == 'dev'
Requires-Dist: types-tqdm; extra == 'dev'
